supply_demand/__init__.py
supply_demand/supply_demand.py
supply_demand-0.1.1.dist-info/METADATA
supply_demand-0.1.1.dist-info/WHEEL
supply_demand-0.1.1.dist-info/licenses/LICENSE
supply_demand-0.1.1.dist-info/RECORD
