Metadata-Version: 2.4
Name: supply-demand
Version: 0.1.1
Summary: Functional dependency paradigm
Project-URL: Homepage, https://github.com/ceil-python/supply-demand
Author-email: Sergey Shkatula <sergey@ceil.dev>
License-Expression: MIT
License-File: LICENSE
Keywords: Supply-Demand,demand,functional,supply
Requires-Python: >=3.7
